discord_msg_lite.py
discord_msg_lite-3.dist-info/METADATA
discord_msg_lite-3.dist-info/WHEEL
discord_msg_lite-3.dist-info/top_level.txt
discord_msg_lite-3.dist-info/RECORD
