Metadata-Version: 2.1
Name: discord-msg-lite
Version: 3
Summary: A simple and lightweight Python PyPI module to send messages easily using Discord Webhooks.
Home-page: https://github.com/YUChoe/discord_msg_lite
Author: Tom YU Choe
Author-email: yonguk.choe@gmail.com
License: MIT
Platform: UNKNOWN
Classifier: Development Status :: 5 - Production/Stable
Classifier: Intended Audience :: Information Technology
Classifier: Intended Audience :: Developers
Classifier: Intended Audience :: System Administrators
Classifier: Programming Language :: Python :: 3
Classifier: Programming Language :: Python :: 3.4
Classifier: Programming Language :: Python :: 3.6
Classifier: Programming Language :: Python :: 3.8
Classifier: Programming Language :: Python :: 3.9
Classifier: License :: OSI Approved :: MIT License
Classifier: Operating System :: OS Independent
